crowdstrike_falcon_foundry-1.0.1.data/data/requirements.txt
crowdstrike_falcon_foundry-1.0.1.dist-info/licenses/LICENSE
falconfoundry/__init__.py
falconfoundry/config_loader.py
falconfoundry/config_loader_fs.py
falconfoundry/context.py
falconfoundry/loader.py
falconfoundry/mapping.py
falconfoundry/model.py
falconfoundry/router.py
falconfoundry/runner.py
falconfoundry/runner_cli.py
falconfoundry/runner_http.py
crowdstrike_falcon_foundry-1.0.1.dist-info/METADATA
crowdstrike_falcon_foundry-1.0.1.dist-info/WHEEL
crowdstrike_falcon_foundry-1.0.1.dist-info/top_level.txt
crowdstrike_falcon_foundry-1.0.1.dist-info/RECORD
